AutoGLM_GUI/__init__.py
AutoGLM_GUI/__main__.py
AutoGLM_GUI/config.py
AutoGLM_GUI/config_manager.py
AutoGLM_GUI/device_manager.py
AutoGLM_GUI/device_metadata_manager.py
AutoGLM_GUI/device_protocol.py
AutoGLM_GUI/exceptions.py
AutoGLM_GUI/history_manager.py
AutoGLM_GUI/i18n.py
AutoGLM_GUI/logger.py
AutoGLM_GUI/metrics.py
AutoGLM_GUI/phone_agent_manager.py
AutoGLM_GUI/platform_utils.py
AutoGLM_GUI/prompt_config.py
AutoGLM_GUI/prompts.py
AutoGLM_GUI/scheduler_manager.py
AutoGLM_GUI/schemas.py
AutoGLM_GUI/scrcpy_protocol.py
AutoGLM_GUI/scrcpy_stream.py
AutoGLM_GUI/server.py
AutoGLM_GUI/socketio_server.py
AutoGLM_GUI/state.py
AutoGLM_GUI/types.py
AutoGLM_GUI/version.py
AutoGLM_GUI/workflow_manager.py
AutoGLM_GUI/actions/__init__.py
AutoGLM_GUI/actions/handler.py
AutoGLM_GUI/actions/types.py
AutoGLM_GUI/adb/__init__.py
AutoGLM_GUI/adb/apps.py
AutoGLM_GUI/adb/connection.py
AutoGLM_GUI/adb/device.py
AutoGLM_GUI/adb/input.py
AutoGLM_GUI/adb/screenshot.py
AutoGLM_GUI/adb/timing.py
AutoGLM_GUI/adb_plus/__init__.py
AutoGLM_GUI/adb_plus/device.py
AutoGLM_GUI/adb_plus/ip.py
AutoGLM_GUI/adb_plus/keyboard_installer.py
AutoGLM_GUI/adb_plus/mdns.py
AutoGLM_GUI/adb_plus/pair.py
AutoGLM_GUI/adb_plus/qr_pair.py
AutoGLM_GUI/adb_plus/screenshot.py
AutoGLM_GUI/adb_plus/serial.py
AutoGLM_GUI/adb_plus/touch.py
AutoGLM_GUI/adb_plus/version.py
AutoGLM_GUI/agents/__init__.py
AutoGLM_GUI/agents/events.py
AutoGLM_GUI/agents/factory.py
AutoGLM_GUI/agents/protocols.py
AutoGLM_GUI/agents/stream_runner.py
AutoGLM_GUI/agents/glm/__init__.py
AutoGLM_GUI/agents/glm/agent.py
AutoGLM_GUI/agents/glm/async_agent.py
AutoGLM_GUI/agents/glm/message_builder.py
AutoGLM_GUI/agents/glm/parser.py
AutoGLM_GUI/agents/glm/prompts_en.py
AutoGLM_GUI/agents/glm/prompts_zh.py
AutoGLM_GUI/agents/mai/__init__.py
AutoGLM_GUI/agents/mai/agent.py
AutoGLM_GUI/agents/mai/parser.py
AutoGLM_GUI/agents/mai/prompts.py
AutoGLM_GUI/agents/mai/traj_memory.py
AutoGLM_GUI/api/__init__.py
AutoGLM_GUI/api/agents.py
autoglm_gui-1.5.5.dist-info/METADATA
autoglm_gui-1.5.5.dist-info/WHEEL
autoglm_gui-1.5.5.dist-info/entry_points.txt
autoglm_gui-1.5.5.dist-info/licenses/LICENSE
autoglm_gui-1.5.5.dist-info/RECORD
