Metadata-Version: 2.4
Name: autoglm-gui
Version: 1.5.5
Summary: Web GUI for AutoGLM Phone Agent - AI-powered Android automation
Project-URL: Homepage, https://github.com/suyiiyii/AutoGLM-GUI
Project-URL: Repository, https://github.com/suyiiyii/AutoGLM-GUI
Author: suyiiyii
License-Expression: Apache-2.0
License-File: LICENSE
Keywords: ai,android,autoglm,automation,gui,phone-agent
Classifier: Development Status :: 3 - Alpha
Classifier: Environment :: Web Environment
Classifier: Framework :: FastAPI
Classifier: Intended Audience :: Developers
Classifier: License :: OSI Approved :: Apache Software License
Classifier: Operating System :: OS Independent
Classifier: Programming Language :: Python :: 3
Classifier: Programming Language :: Python :: 3.10
Classifier: Programming Language :: Python :: 3.11
Classifier: Programming Language :: Python :: 3.12
Classifier: Topic :: Software Development :: Libraries :: Python Modules
Requires-Python: >=3.10
Requires-Dist: apscheduler<4.0.0,>=3.10.0
Requires-Dist: fastapi>=0.124.0
Requires-Dist: fastmcp>=2.0.0
Requires-Dist: httpx[socks]>=0.28.1
Requires-Dist: jinja2>=3.1.0
Requires-Dist: loguru>=0.7.3
Requires-Dist: numpy>=1.24.0
Requires-Dist: openai-agents>=0.6.4
Requires-Dist: openai>=2.9.0
Requires-Dist: pillow>=11.3.0
Requires-Dist: prometheus-client>=0.21.0
Requires-Dist: python-socketio>=5.11.0
Requires-Dist: pyyaml>=6.0.3
Requires-Dist: uvicorn[standard]>=0.38.0
Requires-Dist: zeroconf>=0.148.0
